pysofar/__init__.py
pysofar/sofar.py
pysofar/spotter.py
pysofar/tools.py
pysofar/wavefleet_exceptions.py
pysofar-0.1.16.dist-info/LICENSE.txt
pysofar-0.1.16.dist-info/METADATA
pysofar-0.1.16.dist-info/WHEEL
pysofar-0.1.16.dist-info/top_level.txt
pysofar-0.1.16.dist-info/RECORD
