Metadata-Version: 2.1
Name: pysofar
Version: 0.1.16
Summary: Python client for interfacing with the Sofar Wavefleet API to access Spotter Data
Home-page: https://github.com/wavespotter/wavefleet-client-python
Author: Rufus Sofar
Author-email: sofaroceangithubbot@gmail.com
License: Apache 2 License
Project-URL: Sofar Ocean Site, https://www.sofarocean.com
Project-URL: Spotter About, https://www.sofarocean.com/products/spotter
Project-URL: Spotter Data FAQ, https://www.sofarocean.com/posts/spotter-data-subscription-and-storage
Project-URL: Sofar Dashboard, https://spotter.sofarocean.com/
Project-URL: Sofar Api FAQ, https://spotter.sofarocean.com/api
Platform: UNKNOWN
Classifier: Programming Language :: Python :: 3
Classifier: Programming Language :: Python :: 3.7
Classifier: License :: OSI Approved :: Apache Software License
Classifier: Operating System :: OS Independent
License-File: LICENSE.txt
Requires-Dist: requests
Requires-Dist: python-dotenv
